topsis_py/__init__.py
topsis_py/project1.py
project1_101703386-0.1.dist-info/LICENCE.txt
project1_101703386-0.1.dist-info/METADATA
project1_101703386-0.1.dist-info/WHEEL
project1_101703386-0.1.dist-info/top_level.txt
project1_101703386-0.1.dist-info/RECORD
